evue/__init__.py
evue/basecomponent.py
evue/componentmanager.py
evue/databinding.py
evue/debounce.py
evue/evueapplication.py
evue/fileserver.py
evue/globalthis.py
evue/iconbrowser.py
evue/imagebrowser.py
evue/jstimer.py
evue/log.py
evue/pylock.py
evue/pyrect.py
evue/router.py
evue/sessionobject.py
evue/util.py
evue/elements/__init__.py
evue/elements/base.py
evue/elements/button.py
evue/elements/canvas.py
evue/elements/checkbox.py
evue/elements/collapsible.py
evue/elements/column.py
evue/elements/combobox.py
evue/elements/counter.py
evue/elements/dialog.py
evue/elements/div.py
evue/elements/fletbaseelement.py
evue/elements/grid.py
evue/elements/icon.py
evue/elements/iconbutton.py
evue/elements/image.py
evue/elements/listitem.py
evue/elements/listview.py
evue/elements/markdown.py
evue/elements/progress.py
evue/elements/qrcode.py
evue/elements/responsiverow.py
evue/elements/row.py
evue/elements/slider.py
evue/elements/stackview.py
evue/elements/switch.py
evue/elements/tab.py
evue/elements/tabview.py
evue/elements/text.py
evue/elements/textarea.py
evue/elements/textfield.py
evue/elements/windowtitlebar.py
evue/elements/widgets/__init__.py
evue/elements/widgets/basecontainer.py
evue/elements/widgets/collapsible.py
evue/elements/widgets/counter.py
evue/elements/widgets/evueappbar.py
evue-0.1.6.1.dist-info/LICENSE
evue-0.1.6.1.dist-info/METADATA
evue-0.1.6.1.dist-info/WHEEL
evue-0.1.6.1.dist-info/top_level.txt
evue-0.1.6.1.dist-info/RECORD
