Metadata-Version: 2.1
Name: evue
Version: 0.1.6.1
Summary: Evue is the fastest way to build apps in Python or Javascript on windows/linux/macos/ios/andriod/rtos! Write once, run everywhere! 
Home-page: https://github.com/scriptiot/evm
Author: dragondjf
Author-email: dragondjf <ding465398889@163.com>
License: MIT
Classifier: License :: OSI Approved :: MIT License
Classifier: Operating System :: OS Independent
Classifier: Programming Language :: Python :: 3
Requires-Python: >=3.7
License-File: LICENSE
Requires-Dist: flet (>=0.2.4)
Requires-Dist: pyee (>=9.0.4)
Requires-Dist: loguru (>=0.6.0)
Requires-Dist: pyperclip (>=1.8.2)
Requires-Dist: pillow (>=9.3.0)
Requires-Dist: qrcode (>=7.3.1)
Provides-Extra: dev
